[
  {
    "id": "POLIR-LANCE",
    "label": "Polir la lance?",
    "txt": "Vous avez choisi la Femme-Lézard"
  },
  {
    "label": "Laissez la bouteille",
    "id": "BOUTEILLE",
    "txt": "Vous avez frappé quelqu'un dans la bouche"
  },
  {
    "id": "CHUTE",
    "label": "Le sol amortira la chute",
    "txt": "Vous avez aidé une aliée à s'échapper"
  },
  {
    "label": "Restos du coeur",
    "id": "RESTOS",
    "txt": "Vous avez aidé les nécessiteux"
  },
  {
    "label": "Assurance vie",
    "id": "ASSURANCE",
    "txt": "Apprenez-en plus sur la cathédrale"
  },
  {
    "label": "Le monde a besoin d'un Roi-liche",
    "id": "ROI-LICHE",
    "txt": "Terminez le jeu avec la fin BILLYLUS"
  },
  {
    "label": "Le cheval des trois",
    "id": "TROIE",
    "txt": "Vous avez vaincu les courtisanes"
  },
  {
    "label": "Big Brain Energy",
    "id": "BIG-BRAIN",
    "txt": "Vous avez résolu l'énigme du Facteur"
  },
  {
    "label": "Cul sec",
    "id": "CUL-SEC",
    "txt": "Vous avez vaincu quelqu'un qui avait plus de bouteille que vous"
  },
  {
    "label": "Joli COUP",
    "id": "COUP",
    "txt": "Vous avez trouvé la carte du mercenaire, possiblement sans tricher"
  },
  {
    "label": "Nourris-moi, Seymours!",
    "id": "SEYMOUR",
    "txt": "Vous avez fini dans le vendre d'une plante carnivore, ce sont des choses qui arrivent"
  },
  {
    "label": "Un slip tout neuf",
    "id": "SLIP",
    "txt": "Vous avez fait récurer le vêtement du barbare"
  },
  {
    "id": "FILTRE-JOURNALISTE",
    "label": "Filtre à journaliste",
    "txt": "Vous avez vaincu le général MASSACRE et TERMINE l'Acte 1"
  },
  {
    "id": "REPORTAGE-EXCLUSIF",
    "label": "Reportage exclusif",
    "txt": "Trouvez 4 INFOS ou plus durant l'Acte 1"
  },
  {
    "label": "Parce qu'elles le valent bien",
    "id": "VALENT-BIEN",
    "txt": "Vous avez administré des soins complets"
  },
  {
    "label": "Well. That escalated quickly.",
    "id": "ESCALADED-QUICKLY",
    "txt": "Rencontrez une fin hasardeuse en tombant de votre monture"
  },
  {
    "id": "PUDDING",
    "label": "Le pudding à l'arsenic",
    "txt": "Vous avez vaincu FUNESTE politiquement"
  },
  {
    "id": "SAFEWORD",
    "label": "C'était quoi le safeword?",
    "txt": "Vous avez vaincu FUNESTE avec l'aide de vos amis"
  },
  {
    "label": "Tout ça pour ça",
    "id": "TOUT-CA-POUR-CA",
    "txt": "Vous avez ouvert le trésor du sorcier"
  },
  {
    "label": "Cercle vicieux",
    "id": "CERCLE-VICIEUX",
    "txt": "Vous avez péri en tentant de sauver le barbare d'une situation impossible"
  },
  {
    "label": "Secret d'histoire",
    "id": "SECRET-HISTOIRE",
    "txt": "Apprenez-en plus sur le quartier historique"
  },
  {
    "label": "Calamity Billy",
    "id": "CALAMITY-BILLY",
    "txt": "Affrontez les agents de la maréchaussée dans leur QG en combat singulier"
  },
  {
    "label": "FBI! OPEN UP!",
    "id": "FBI",
    "txt": "Vous avez fait une entré facassante"
  },
  {
    "label": "L'innocent",
    "id": "INNOCENT",
    "txt": "Laissez le rituel se conclure ou ratez son interruption"
  },
  {
    "label": "Chut!",
    "id": "CHUT",
    "txt": "Vous avez fait ami-ami avec la Bibliothècaire"
  },
  {
    "label": "Billy Ultra Instinct",
    "id": "ULTRA-INSTINCT",
    "txt": "Vous avez reçu une aide inespérée"
  },
  {
    "label": "Bière qui roule...",
    "id": "BIERE",
    "txt": "Vous avez déclenché une bagarre générale"
  },
  {
    "label": "Une misérable petite pile de secrets",
    "id": "PILE-SECRETS",
    "txt": "Vous avez poliement décliné l'offre d'une créature"
  },
  {
    "id": "ENFANT-DRAGON",
    "label": "Billy Enfant-de-Dragon",
    "txt": "Soumettez le dragon à la loyale"
  },
  {
    "label": "Billy Stardust",
    "id": "STARDUST",
    "txt": "Vous avez choisi le Plaisancier"
  },
  {
    "label": "Soyez témoins!!",
    "id": "TEMOINS",
    "txt": "Vous avez atteint la fin GLOIRE MAX"
  },
  {
    "label": "Pas d'omelette sans cassé du fion",
    "id": "OMELETTE",
    "txt": "Vous avez provoqué votre adversaire"
  },
  {
    "label": "Culture Pub",
    "id": "CULTURE-PUB",
    "txt": "Vous avez trouvé un produit célèbre"
  },
  {
    "label": "La vie est belle",
    "id": "VIE-BELLE",
    "txt": "Vous avez protégé les enfants des horreurs de la guerre"
  },
  {
    "label": "Mémoire honorée",
    "id": "MEMOIRE-HONOREE",
    "txt": "Vous avez atteint la fin RICHESSE MAX"
  },
  {
    "label": "Par Toutatis",
    "id": "TOUTATIS",
    "txt": "Vous avez laissé le barbare improviser"
  },
  {
    "label": "Un émeu dans un magasin de porcelaine",
    "id": "EMEU-PORCELAINE",
    "txt": "Lâcher Mimine dans le laboratoire de l'Acte IV"
  },
  {
    "id": "OCTOGONE",
    "label": "Octogone",
    "txt": "Battez l'adversaire final de l'arène et récupérez la CEINTURE DE CHAMPION"
  },
  {
    "label": "J'ai eu la chance d'être appelé le premier",
    "id": "PREMIER",
    "txt": "Vous vous êtes débarassé des occupants de la taverne"
  },
  {
    "id": "SORS",
    "label": "Sors! Sors! T'as la clé!",
    "txt": "Vous avez aidé une aliée à s'échapper"
  },
  {
    "label": "Toujours vivant! Ha!",
    "id": "VIVANT",
    "txt": "Terminez le jeu avec un Billy PRUDENT"
  },
  {
    "id": "FIL-EPEE",
    "label": "Au fil de l'épée",
    "txt": "Vous avez vaincu MORTELLE avec l'aide de vos amis"
  },
  {
    "id": "BULIAAA",
    "label": "Buliaaa !!!",
    "txt": "Terminez le jeu avec un Billy GUERRIER"
  },
  {
    "label": "Travail Terminé!",
    "id": "TRAVAIL-TERMINE",
    "txt": "Terminez le jeu avec un Billy PAYSAN"
  },
  {
    "label": "Dites-le avec de fleurs",
    "id": "FLEURS",
    "txt": "Terminez le jeu avec la fin alternative PRUDENT"
  },
  {
    "label": "Pour l'honneur",
    "id": "HONNEUR",
    "txt": "Terminez le jeu avec la fin alternative GUERRIER"
  },
  {
    "label": "Pff...Rien de personnel!",
    "id": "PERSONNEL",
    "txt": "Terminez le jeu avec un Billy DEBROUILLARD"
  },
  {
    "label": "Arsène Billy",
    "id": "ARSENE",
    "txt": "Terminez le jeu avec la fin alternative DEBROUILLARD"
  },
  {
    "label": "METAAAL!!!",
    "id": "METAAAL",
    "txt": "Rencontrez une fin stylée dans les flammes du phénix"
  },
  {
    "label": "Un sabot pour deux",
    "id": "SABOT",
    "txt": "Terminez le jeu avec la fin alternative PAYSAN"
  },
  {
    "label": "Tu quoque Billy?",
    "id": "TU-QUOQUE-BILLY",
    "txt": "Terminez le jeu avec la fin secrète PRUDENT"
  }
]